diginlineprofiler/__init__.py
diginlineprofiler/_frontend.py
diginlineprofiler/_version.py
diginlineprofiler/profile_lib.py
diginlineprofiler/utils.py
diginlineprofiler/visualizer.py
diginlineprofiler/labextension/build_log.json
diginlineprofiler/labextension/package.json
diginlineprofiler/labextension/static/lib_index_js.cafb5028f8ca970a4838.js
diginlineprofiler/labextension/static/lib_index_js.cafb5028f8ca970a4838.js.map
diginlineprofiler/labextension/static/remoteEntry.f7a24f928e432e07aba3.js
diginlineprofiler/labextension/static/remoteEntry.f7a24f928e432e07aba3.js.map
diginlineprofiler/labextension/static/style.js
diginlineprofiler/nbextension/extension.js
diginlineprofiler/nbextension/index.js
diginlineprofiler/nbextension/index.js.LICENSE.txt
diginlineprofiler-0.1.2.data/data/share/jupyter/labextensions/diginlineprofiler/build_log.json
diginlineprofiler-0.1.2.data/data/share/jupyter/labextensions/diginlineprofiler/install.json
diginlineprofiler-0.1.2.data/data/share/jupyter/labextensions/diginlineprofiler/package.json
diginlineprofiler-0.1.2.data/data/share/jupyter/labextensions/diginlineprofiler/static/lib_index_js.cafb5028f8ca970a4838.js
diginlineprofiler-0.1.2.data/data/share/jupyter/labextensions/diginlineprofiler/static/lib_index_js.cafb5028f8ca970a4838.js.map
diginlineprofiler-0.1.2.data/data/share/jupyter/labextensions/diginlineprofiler/static/remoteEntry.f7a24f928e432e07aba3.js
diginlineprofiler-0.1.2.data/data/share/jupyter/labextensions/diginlineprofiler/static/remoteEntry.f7a24f928e432e07aba3.js.map
diginlineprofiler-0.1.2.data/data/share/jupyter/labextensions/diginlineprofiler/static/style.js
diginlineprofiler-0.1.2.dist-info/METADATA
diginlineprofiler-0.1.2.dist-info/WHEEL
diginlineprofiler-0.1.2.dist-info/top_level.txt
diginlineprofiler-0.1.2.dist-info/RECORD
